dictionary/__init__.py
dictionary/dictionary.py
metehanDictionary886-2.0.0.dist-info/METADATA
metehanDictionary886-2.0.0.dist-info/WHEEL
metehanDictionary886-2.0.0.dist-info/top_level.txt
metehanDictionary886-2.0.0.dist-info/RECORD
